.gitignore
AUTHORS.rst
HISTORY.rst
LICENSE
README.rst
requirements.txt
setup.py
deescalate/__init__.py
deescalate/cd.pxd
deescalate/cd.pyx
deescalate/constants.py
deescalate/main.py
deescalate/script.py
deescalate/utils.py
deescalate.egg-info/PKG-INFO
deescalate.egg-info/SOURCES.txt
deescalate.egg-info/dependency_links.txt
deescalate.egg-info/entry_points.txt
deescalate.egg-info/not-zip-safe
deescalate.egg-info/top_level.txt
docs/Makefile
docs/api.rst
docs/authors.rst
docs/conf.py
docs/deescalate.rst
docs/history.rst
docs/index.rst
docs/installation.rst
docs/modules.rst
docs/overview.rst
docs/readme.rst
docs/wrapper.rst
docs/static_build/html/.buildinfo
docs/static_build/html/api.html
docs/static_build/html/authors.html
docs/static_build/html/deescalate.html
docs/static_build/html/genindex.html
docs/static_build/html/history.html
docs/static_build/html/index.html
docs/static_build/html/installation.html
docs/static_build/html/modules.html
docs/static_build/html/objects.inv
docs/static_build/html/overview.html
docs/static_build/html/py-modindex.html
docs/static_build/html/readme.html
docs/static_build/html/search.html
docs/static_build/html/searchindex.js
docs/static_build/html/wrapper.html
docs/static_build/html/_modules/index.html
docs/static_build/html/_modules/deescalate/constants.html
docs/static_build/html/_modules/deescalate/main.html
docs/static_build/html/_sources/api.txt
docs/static_build/html/_sources/authors.txt
docs/static_build/html/_sources/deescalate.txt
docs/static_build/html/_sources/history.txt
docs/static_build/html/_sources/index.txt
docs/static_build/html/_sources/installation.txt
docs/static_build/html/_sources/modules.txt
docs/static_build/html/_sources/overview.txt
docs/static_build/html/_sources/readme.txt
docs/static_build/html/_sources/wrapper.txt
docs/static_build/html/_static/ajax-loader.gif
docs/static_build/html/_static/basic.css
docs/static_build/html/_static/comment-bright.png
docs/static_build/html/_static/comment-close.png
docs/static_build/html/_static/comment.png
docs/static_build/html/_static/doctools.js
docs/static_build/html/_static/down-pressed.png
docs/static_build/html/_static/down.png
docs/static_build/html/_static/file.png
