Metadata-Version: 1.1
Name: deescalate
Version: 0.1.2
Summary: using linux capabilities to drop privileges in python
Home-page: https://github.com/stephane-martin/deescalate
Author: Stephane Martin
Author-email: stephane.martin_github@vesperal.eu
License: LGPLv3+
Keywords: linux cython python capabilities root prctl securebits privileges
Platform: UNKNOWN
Classifier: Development Status :: 3 - Alpha
Classifier: Intended Audience :: Developers
Classifier: Intended Audience :: System Administrators
Classifier: License :: OSI Approved :: GNU Lesser General Public License v3 or later (LGPLv3+)
Classifier: Natural Language :: English
Classifier: Programming Language :: Python :: 2.7
Classifier: Environment :: Console
Classifier: Operating System :: POSIX :: Linux
